cellplot/__init__.py
cellplot/images.py
cellplot/multiview.py
cellplot/patches.py
cellplot/segmentation.py
cellplot/utils.py
cellplot-1.12.dist-info/METADATA
cellplot-1.12.dist-info/WHEEL
cellplot-1.12.dist-info/top_level.txt
cellplot-1.12.dist-info/RECORD
