Metadata-Version: 2.1
Name: cellplot
Version: 1.12
Home-page: https://github.com/SimonBon/cellplot
Author: Simon Gutwein
Author-email: simon.gutwein@ccri.at
License: MIT
Classifier: License :: OSI Approved :: MIT License
Classifier: Programming Language :: Python
Classifier: Programming Language :: Python :: 3
Classifier: Programming Language :: Python :: 3.9
Requires-Dist: numpy
Requires-Dist: matplotlib
Requires-Dist: pathlib
Requires-Dist: pillow
Requires-Dist: opencv-python
Requires-Dist: scipy
